Workbook

Sheet Sheet1
C1: D'Mart Dataset
A3: Date | B3: Invoice_ID | C3: Customer_ID | D3: Product_Name | E3: Product_Category | F3: Quantity | G3: Unit_Price | H3: Discount | I3: Payment_Method | J3: Store_Location
A4: 46204 | B4: INV0001 | C4: CUST112 | D4: Soap | E4: Stationery | F4: 2 | G4: 100 | H4: 20 | I4: Cash | J4: Aurangabad
A5: 46205 | B5: INV0002 | C5: CUST108 | D5: Soap | E5: Grocery | F5: 3 | G5: 100 | H5: 10 | I5: Cash | J5: Pune
A6: 46206 | B6: INV0003 | C6: CUST104 | D6: Pen | E6: Stationery | F6: 2 | G6: 400 | H6: 20 | I6: Card | J6: Nashik
A7: 46207 | B7: INV0004 | C7: CUST113 | D7: Notebook | E7: Stationery | F7: 2 | G7: 100 | H7: 0 | I7: Card | J7: Pune
A8: 46208 | B8: INV0005 | C8: CUST114 | D8: Shoes | E8: Clothing | F8: 1 | G8: 100 | H8: 0 | I8: Cash | J8: Mumbai
A9: 46209 | B9: INV0006 | C9: CUST113 | D9: Shoes | E9: Stationery | F9: 5 | G9: 50 | H9: 10 | I9: Cash | J9: Nagpur
A10: 46210 | B10: INV0007 | C10: CUST110 | D10: Milk 1L | E10: Home | F10: 4 | G10: 100 | H10: 0 | I10: Card | J10: Nashik
A11: 46211 | B11: INV0008 | C11: CUST108 | D11: Mixer | E11: Electronics | F11: 1 | G11: 400 | H11: 0 | I11: Upi | J11: Pune
A12: 46212 | B12: INV0009 | C12: CUST103 | D12: Milk 1L | E12: Home | F12: 1 | G12: 200 | H12: 10 | I12: Upi | J12: Nagpur
A13: 46213 | B13: INV0010 | C13: CUST120 | D13: Soap | E13: Electronics | F13: 5 | G13: 100 | H13: 20 | I13: Upi | J13: Mumbai
A14: 46214 | B14: INV0011 | C14: CUST111 | D14: Soap | E14: Clothing | F14: 4 | G14: 400 | H14: 10 | I14: Card | J14: Pune
A15: 46215 | B15: INV0012 | C15: CUST102 | D15: Mobile Phone | E15: Stationery | F15: 2 | G15: 20000 | H15: 0 | I15: Cash | J15: Aurangabad
A16: 46216 | B16: INV0013 | C16: CUST119 | D16: Mobile Phone | E16: Clothing | G16: 15000 | H16: 0 | I16: Cash | J16: Mumbai
A17: 46217 | B17: INV0014 | C17: CUST118 | D17: Milk 1L | E17: Electronics | F17: 1 | G17: 50 | H17: 0 | I17: Cash | J17: Aurangabad
A18: 46218 | B18: INV0015 | C18: CUST114 | D18: Rice 5Kg | E18: Stationery | F18: 5 | G18: 400 | H18: 0 | I18: Cash | J18: Mumbai
A19: 46219 | B19: INV0016 | C19: CUST103 | D19: T-Shirt | E19: Stationery | F19: 1 | G19: 20000 | H19: 10 | I19: Card | J19: Nagpur
A20: 46220 | B20: INV0017 | C20: CUST118 | D20: Soap | E20: Grocery | F20: 4 | G20: 400 | H20: 0 | I20: Upi | J20: Nashik
A21: 46221 | B21: INV0018 | C21: CUST108 | D21: Milk 1L | E21: Stationery | G21: 400 | H21: 20 | I21: Upi | J21: Nagpur
A22: 46222 | B22: INV0019 | C22: CUST101 | D22: Soap | E22: Stationery | F22: 2 | G22: 100 | H22: 0 | I22: Card | J22: Pune
A23: 46223 | B23: INV0020 | C23: CUST112 | D23: Mixer | E23: Stationery | F23: 2 | G23: 450 | H23: 20 | I23: Card | J23: Pune
A24: 46224 | B24: INV0021 | C24: CUST111 | D24: Shoes | E24: Clothing | G24: 100 | H24: 20 | I24: Upi | J24: Nagpur
A25: 46225 | B25: INV0022 | C25: CUST105 | D25: Milk 1L | E25: Stationery | F25: 2 | G25: 15000 | H25: 0 | I25: Upi | J25: Nashik
A26: 46226 | B26: INV0023 | C26: CUST118 | D26: Soap | E26: Home | F26: 2 | G26: 450 | H26: 20 | I26: Upi | J26: Aurangabad
A27: 46227 | B27: INV0024 | C27: CUST111 | D27: Mixer | E27: Stationery | F27: 1 | G27: 200 | H27: 10 | I27: Card | J27: Pune
A28: 46228 | B28: INV0025 | C28: CUST108 | D28: Milk 1L | E28: Electronics | F28: =COUNT(F21) -> 0 | G28: 100 | H28: 0 | I28: Cash | J28: Pune
A29: 46229 | B29: INV0026 | C29: CUST108 | D29: Shoes | E29: Electronics | F29: 1 | G29: 450 | H29: 20 | I29: Upi | J29: Pune
A30: 46230 | B30: INV0027 | C30: CUST106 | D30: Soap | E30: Stationery | F30: 4 | G30: 100 | H30: 20 | I30: Cash | J30: Nashik
A31: 46231 | B31: INV0028 | C31: CUST106 | D31: Mobile Phone | E31: Clothing | F31: 1 | G31: 15000 | H31: 10 | I31: Card | J31: Pune
A32: 46232 | B32: INV0029 | C32: CUST106 | D32: Rice 5Kg | E32: Stationery | F32: 5 | G32: 200 | H32: 10 | I32: Card | J32: Pune
A33: 46233 | B33: INV0030 | C33: CUST106 | D33: Tv | E33: Grocery | F33: 5 | G33: 50 | H33: 0 | I33: Upi | J33: Nagpur
B34: INV0031 | C34: CUST117 | D34: Shoes | E34: Clothing | F34: 2 | G34: 400 | H34: 0 | I34: Cash | J34: Aurangabad
A35: 46235 | B35: INV0032 | C35: CUST100 | D35: Mixer | E35: Electronics | F35: 5 | G35: 100 | H35: 0 | I35: Card | J35: Pune
A36: 46236 | B36: INV0033 | C36: CUST104 | D36: Pen | E36: Clothing | F36: 5 | G36: 100 | H36: 10 | I36: Card | J36: Mumbai
A37: 46237 | B37: INV0034 | C37: CUST116 | D37: Notebook | E37: Grocery | F37: 5 | G37: 450 | H37: 0 | I37: Card | J37: Nashik
A38: 46238 | B38: INV0035 | C38: CUST113 | D38: Pen | E38: Electronics | F38: 5 | G38: 100 | H38: 20 | I38: Card | J38: Nashik
A39: 46239 | B39: INV0036 | C39: CUST115 | D39: Mobile Phone | E39: Clothing | F39: 2 | G39: 200 | H39: 20 | I39: Card | J39: Aurangabad
A40: 46240 | B40: INV0037 | C40: CUST105 | D40: Mixer | E40: Electronics | F40: 2 | G40: 450 | H40: 0 | I40: Cash | J40: Nagpur
A41: 46241 | B41: INV0038 | C41: CUST111 | D41: Mixer | E41: Home | G41: 20000 | H41: 0 | I41: Upi | J41: Nagpur
A42: 46242 | B42: INV0039 | C42: CUST100 | D42: Rice 5Kg | E42: Stationery | F42: 5 | G42: 450 | H42: 20 | I42: Cash | J42: Nagpur
A43: 46243 | B43: INV0040 | C43: CUST104 | D43: Mixer | E43: Stationery | F43: 1 | G43: 20000 | H43: 20 | I43: Cash | J43: Nashik
A44: 46244 | B44: INV0041 | C44: CUST100 | D44: Soap | E44: Clothing | F44: 3 | G44: 15000 | H44: 0 | I44: Card | J44: Pune
A45: 46245 | B45: INV0042 | C45: CUST106 | D45: Tv | E45: Clothing | F45: 4 | G45: 50 | H45: 0 | I45: Cash | J45: Mumbai
A46: 46246 | B46: INV0043 | C46: CUST102 | D46: Tv | E46: Electronics | F46: 4 | G46: 400 | H46: 20 | I46: Upi | J46: Pune
A47: 46247 | B47: INV0044 | C47: CUST112 | D47: Pen | E47: Clothing | F47: 2 | G47: 450 | H47: 20 | I47: Card | J47: Nagpur
A48: 46248 | B48: INV0045 | C48: CUST104 | D48: Milk 1L | E48: Stationery | G48: 20000 | H48: 0 | I48: Card | J48: Nagpur
A49: 46249 | B49: INV0046 | C49: CUST116 | D49: Tv | E49: Grocery | F49: 2 | G49: 100 | H49: 0 | I49: Upi | J49: Aurangabad
A50: 46250 | B50: INV0047 | C50: CUST119 | D50: Milk 1L | E50: Home | G50: 450 | H50: 0 | I50: Card | J50: Mumbai
A51: 46251 | B51: INV0048 | C51: CUST109 | D51: Milk 1L | E51: Grocery | F51: 2 | G51: 50 | H51: 0 | I51: Cash | J51: Nagpur
A52: 46252 | B52: INV0049 | C52: CUST112 | D52: T-Shirt | E52: Electronics | F52: 5 | G52: 15000 | H52: 0 | I52: Cash | J52: Nashik
A53: 46253 | B53: INV0050 | C53: CUST105 | D53: Pen | E53: Home | F53: 3 | G53: 50 | H53: 0 | I53: Cash | J53: Pune
A54: 46254 | B54: INV0051 | C54: CUST119 | D54: T-Shirt | E54: Clothing | F54: 4 | G54: 400 | H54: 10 | I54: Card | J54: Pune
A55: 46255 | B55: INV0052 | C55: CUST112 | D55: Soap | E55: Electronics | F55: 2 | G55: 400 | H55: 0 | I55: Upi | J55: Nashik
A56: 46256 | B56: INV0053 | C56: CUST107 | D56: Soap | E56: Electronics | F56: 5 | G56: 450 | H56: 0 | I56: Card | J56: Nashik
A57: 46257 | B57: INV0054 | C57: CUST102 | D57: Shoes | E57: Home | F57: 2 | G57: 15000 | H57: 0 | I57: Card | J57: Nashik
A58: 46258 | B58: INV0055 | C58: CUST110 | D58: T-Shirt | E58: Grocery | F58: 1 | G58: 15000 | H58: 0 | I58: Cash | J58: Nashik
A59: 46259 | B59: INV0056 | C59: CUST103 | D59: Rice 5Kg | E59: Stationery | F59: 3 | G59: 200 | H59: 20 | I59: Card | J59: Aurangabad
A60: 46260 | B60: INV0057 | C60: CUST119 | D60: Mobile Phone | E60: Clothing | F60: 1 | G60: 200 | H60: 20 | I60: Card | J60: Pune
A61: 46261 | B61: INV0058 | C61: CUST114 | D61: Notebook | E61: Grocery | F61: 2 | G61: 200 | H61: 0 | I61: Cash | J61: Mumbai
A62: 46262 | B62: INV0059 | C62: CUST108 | D62: Soap | E62: Electronics | F62: 2 | G62: 20000 | H62: 0 | I62: Card | J62: Nashik
... A76: 46276 | B76: INV0073 | C76: CUST116 | D76: Mobile Phone | E76: Stationery | F76: 1 | G76: 450 | H76: 10 | I76: Card | J76: Aurangabad
A77: 46277 | B77: INV0074 | C77: CUST119 | D77: T-Shirt | E77: Electronics | G77: 20000 | H77: 20 | I77: Upi | J77: Aurangabad
A78: 46278 | B78: INV0075 | C78: CUST116 | D78: Milk 1L | E78: Grocery | F78: 3 | G78: 20000 | H78: 0 | I78: Upi | J78: Mumbai
A79: 46279 | B79: INV0076 | C79: CUST103 | D79: Notebook | E79: Clothing | F79: 2 | G79: 20000 | H79: 0 | I79: Card | J79: Aurangabad
A80: 46280 | B80: INV0077 | C80: CUST104 | D80: Shoes | E80: Home | F80: 5 | G80: 400 | H80: 20 | I80: Upi | J80: Nashik
A81: 46281 | B81: INV0078 | C81: CUST108 | D81: Rice 5Kg | E81: Home | F81: 1 | G81: 100 | H81: 0 | I81: Card | J81: Nashik
A82: 46282 | B82: INV0079 | C82: CUST119 | D82: Rice 5Kg | E82: Grocery | F82: 2 | G82: 20000 | H82: 10 | I82: Upi | J82: Nashik
A83: 46283 | B83: INV0080 | C83: CUST109 | D83: Rice 5Kg | E83: Home | F83: 2 | G83: 50 | H83: 20 | I83: Card | J83: Mumbai
A84: 46284 | B84: INV0081 | C84: CUST103 | D84: Milk 1L | E84: Clothing | F84: 2 | G84: 15000 | H84: 10 | I84: Upi | J84: Nashik
A85: 46285 | B85: INV0082 | C85: CUST104 | D85: T-Shirt | E85: Home | F85: 2 | G85: 20000 | H85: 10 | I85: Upi | J85: Nashik
A86: 46286 | B86: INV0083 | C86: CUST104 | D86: Soap | E86: Home | F86: 3 | G86: 200 | H86: 20 | I86: Cash | J86: Pune
A87: 46287 | B87: INV0084 | C87: CUST113 | D87: Pen | E87: Home | F87: 4 | G87: 50 | H87: 20 | I87: Cash | J87: Nagpur
A88: 46288 | B88: INV0085 | C88: CUST112 | D88: Milk 1L | E88: Clothing | F88: 2 | G88: 450 | H88: 20 | I88: Card | J88: Pune
A89: 46289 | B89: INV0086 | C89: CUST105 | D89: Shoes | E89: Clothing | F89: 2 | G89: 20000 | H89: 0 | I89: Upi | J89: Aurangabad
A90: 46290 | B90: INV0087 | C90: CUST113 | D90: Shoes | E90: Stationery | G90: 450 | H90: 10 | I90: Card | J90: Nashik
A91: 46291 | B91: INV0088 | C91: CUST116 | D91: Soap | E91: Clothing | F91: 2 | G91: 100 | H91: 0 | I91: Cash | J91: Aurangabad
A92: 46292 | B92: INV0089 | C92: CUST115 | D92: Soap | E92: Clothing | F92: 4 | G92: 15000 | H92: 20 | I92: Card | J92: Aurangabad
A93: 46293 | B93: INV0090 | C93: CUST106 | D93: Tv | E93: Clothing | F93: 2 | G93: 100 | H93: 20 | I93: Card | J93: Aurangabad
A94: 46294 | B94: INV0091 | C94: CUST120 | D94: Mixer | E94: Electronics | G94: 50 | H94: 20 | I94: Cash | J94: Mumbai
A95: 46295 | B95: INV0092 | C95: CUST117 | D95: Shoes | E95: Clothing | F95: 5 | G95: 200 | H95: 0 | I95: Card | J95: Pune
A96: 46296 | B96: INV0093 | C96: CUST100 | D96: Mobile Phone | E96: Electronics | F96: 3 | G96: 50 | H96: 0 | I96: Upi | J96: Aurangabad
A97: 46297 | B97: INV0094 | C97: CUST104 | D97: T-Shirt | E97: Grocery | F97: 2 | G97: 20000 | H97: 0 | I97: Upi | J97: Nashik
A98: 46298 | B98: INV0095 | C98: CUST101 | D98: Mobile Phone | E98: Clothing | F98: 1 | G98: 200 | H98: 20 | I98: Cash | J98: Nagpur
A99: 46299 | B99: INV0096 | C99: CUST103 | D99: Notebook | E99: Electronics | F99: 2 | G99: 400 | H99: 0 | I99: Cash | J99: Aurangabad
A100: 46300 | B100: INV0097 | C100: CUST100 | D100: Rice 5Kg | E100: Stationery | G100: 450 | H100: 10 | I100: Card | J100: Mumbai
A101: 46301 | B101: INV0098 | C101: CUST115 | D101: T-Shirt | E101: Stationery | F101: 1 | G101: 50 | H101: 0 | I101: Upi | J101: Nagpur
A102: 46302 | B102: INV0099 | C102: CUST105 | D102: Notebook | E102: Stationery | F102: 2 | G102: 400 | H102: 20 | I102: Cash | J102: Aurangabad
A103: 46303 | B103: INV0100 | C103: CUST113 | D103: Mixer | E103: Stationery | F103: 2 | G103: 15000 | H103: 0 | I103: Upi | J103: Pune
A104: 46304 | B104: INV0101 | C104: CUST105 | D104: Tv | E104: Stationery | F104: 3 | G104: 200 | H104: 0 | I104: Cash | J104: Mumbai
A105: 46305 | B105: INV0102 | C105: CUST115 | D105: Mixer | E105: Electronics | F105: 3 | G105: 15000 | H105: 20 | I105: Cash | J105: Nashik
A106: 46306 | B106: INV0103 | C106: CUST113 | D106: Pen | E106: Grocery | G106: 200 | H106: 0 | I106: Upi | J106: Aurangabad
A107: 46307 | B107: INV0104 | C107: CUST105 | D107: Soap | E107: Stationery | F107: 2 | G107: 50 | H107: 0 | I107: Upi | J107: Nagpur
A108: 46308 | B108: INV0105 | C108: CUST102 | D108: Rice 5Kg | E108: Electronics | F108: 3 | G108: 100 | H108: 0 | I108: Card | J108: Mumbai
A109: 46309 | B109: INV0106 | C109: CUST111 | D109: Pen | E109: Clothing | F109: 5 | G109: 450 | H109: 10 | I109: Cash | J109: Pune
A110: 46310 | B110: INV0107 | C110: CUST109 | D110: Milk 1L | E110: Electronics | F110: 2 | G110: 200 | H110: 20 | I110: Upi | J110: Nashik
A111: 46311 | B111: INV0108 | C111: CUST100 | D111: T-Shirt | E111: Electronics | F111: 1 | G111: 200 | H111: 0 | I111: Upi | J111: Mumbai
A112: 46312 | B112: INV0109 | C112: CUST115 | D112: Milk 1L | E112: Clothing | F112: 2 | G112: 15000 | H112: 0 | I112: Cash | J112: Mumbai
A113: 46313 | B113: INV0110 | C113: CUST111 | D113: Mobile Phone | E113: Home | F113: 4 | G113: 400 | H113: 10 | I113: Cash | J113: Pune
A114: 46314 | B114: INV0111 | C114: CUST103 | D114: Milk 1L | E114: Clothing | F114: 4 | G114: 15000 | H114: 0 | I114: Upi | J114: Nagpur
...

Sheet Sheet2
A1: EDA
A3: Unit price | B3: values | D3: Discount | E3: values
A4: sum | B4: =SUM(Sheet1!G4:G153) -> 687150 | D4: sum | E4: =SUM(Sheet1!H4:H153) -> 1170
A5: min | B5: =MIN(Sheet1!G4:G153) -> 50 | D5: min | E5: =MIN(Sheet1!H4:H153) -> 0
A6: max | B6: =MAX(Sheet1!G4:G153) -> 20000 | D6: max | E6: =MAX(Sheet1!H4:H153) -> 20
A7: ava | B7: =AVERAGE(Sheet1!G4:G153) -> 4581 | D7: ava | E7: =AVERAGE(Sheet1!H4:H153) -> 7.8
A8: mean | B8: 4581 | D8: mean | E8: 4581
A9: mode | B9: {=MODE(Sheet1!G4:G153)} -> 200 | D9: mode | E9: {=MODE(Sheet1!H4:H153)} -> 0
A10: medium | B10: =MEDIAN(Sheet1!G4:G153) -> 400 | D10: medium | E10: =MEDIAN(Sheet1!H4:H153) -> 5
A11: sd | B11: =STDEV(Sheet1!G4:G153) -> 7711.8963 | D11: sd | E11: =STDEV(Sheet1!H4:H153) -> 8.5820165
A14: Pivote colume
E15: Total order
A16: Product name | B16: Sales price | C16: Quantity
A17: Milk 1L | B17: =SUM(Sheet1!G10:G145) -> 625250 | C17: =SUM(Sheet1!F10:F145) -> 322 | E17: Order | F17: 150
A18: Mixer | B18: =SUM(Sheet1!G11:G140) -> 609650 | C18: =SUM(Sheet1!F11:F140) -> 306
A19: Mobile Phone | B19: =SUM(Sheet1!G15:G147) -> 624150 | C19: =SUM(Sheet1!F15:F147) -> 313
A20: Notebook | B20: =SUM(Sheet1!G7:G136) -> 594550 | C20: =SUM(Sheet1!F7:F136) -> 305
A21: Pen | B21: =SUM(Sheet1!G6:G150) -> 666400 | C21: =SUM(Sheet1!F6:F150) -> 348
A22: Rice 5Kg | B22: =SUM(Sheet1!G18:G153) -> 650050 | C22: =SUM(Sheet1!F18:F153) -> 325
A23: Shoes | B23: =SUM(Sheet1!G8:G124) -> 571150 | C23: =SUM(Sheet1!F8:F124) -> 277
A24: Soap | B24: =SUM(Sheet1!G4:G149) -> 646600 | C24: =SUM(Sheet1!F4:F149) -> 351
A25: T-Shirt | B25: =SUM(Sheet1!G19:G148) -> 608700 | C25: =SUM(Sheet1!F19:F148) -> 310
A26: Tv | B26: =SUM(Sheet1!G33:G152) -> 576700 | C26: =SUM(Sheet1!F33:F152) -> 295
